logicDS
